dremio_mcp/__init__.py
dremio_mcp/cli.py
dremio_mcp/config.py
dremio_mcp/prompts.py
dremio_mcp/server.py
dremio_mcp/tools/catalog.py
dremio_mcp/tools/docs.py
dremio_mcp/tools/jobs.py
dremio_mcp/tools/query.py
dremio_mcp/tools/reflection.py
dremio_mcp/tools/semantic.py
dremio_mcp/utils/docs_helper.py
dremio_mcp/utils/dremio_client.py
tests/conftest.py
tests/diagnose_sys_jobs.py
tests/test_catalog.py
tests/test_docs.py
tests/test_enhancements_live.py
tests/test_enhancements_mock.py
tests/test_jobs.py
tests/test_query.py
tests/test_reflection.py
tests/test_semantic.py
tests/verify_all_live.py
tests/verify_wiki_tags.py
dremio_local_mcp-0.5.0.dist-info/METADATA
dremio_local_mcp-0.5.0.dist-info/WHEEL
dremio_local_mcp-0.5.0.dist-info/entry_points.txt
dremio_local_mcp-0.5.0.dist-info/top_level.txt
dremio_local_mcp-0.5.0.dist-info/RECORD
