Metadata-Version: 2.4
Name: dremio-local-mcp
Version: 0.5.0
Summary: A Model Context Protocol (MCP) server for Dremio
Author-email: Alex Merced <alex.merced@dremio.com>
Requires-Python: >=3.10
Requires-Dist: fastmcp
Requires-Dist: requests
Requires-Dist: pyyaml
Requires-Dist: rich
Requires-Dist: dremio-cli>=1.11.0
Requires-Dist: pytest
Requires-Dist: pytest-asyncio
